GreenPoster/__init__.py
GreenPoster/core.py
greenposter-0.1.5.dist-info/licenses/LICENSE
greenposter-0.1.5.dist-info/METADATA
greenposter-0.1.5.dist-info/WHEEL
greenposter-0.1.5.dist-info/top_level.txt
greenposter-0.1.5.dist-info/RECORD
