Metadata-Version: 2.4
Name: GreenPoster
Version: 0.1.5
Summary: A Python library for text rendering on images with green-based compositing.
Author: Codedash
License: MIT
Requires-Python: >=3.8
License-File: LICENSE
Requires-Dist: Pillow>=10.0.0
Requires-Dist: numpy>=1.23.0
Requires-Dist: toml
Requires-Dist: pydantic>=2.0.0
Requires-Dist: opencv-python>=4.9.0
Dynamic: license-file
